README.md
setup.cfg
setup.py
ratter/__init__.py
ratter/expressions.py
ratter/layer.py
ratter/material.py
ratter/stack.py
ratter/symbols.py
ratter/version.py
ratter.egg-info/PKG-INFO
ratter.egg-info/SOURCES.txt
ratter.egg-info/dependency_links.txt
ratter.egg-info/requires.txt
ratter.egg-info/top_level.txt