Metadata-Version: 2.1
Name: ratter
Version: 0.1.0a0
Summary: calculate coherent reflection, absorption
Home-page: https://github.com/fa-me/ratter
Author: Fabian Meyer
Author-email: fabian.meyer@ise.fraunhofer.de
License: UNKNOWN
Platform: UNKNOWN
Classifier: Development Status :: 3 - Alpha
Classifier: Intended Audience :: Science/Research
Classifier: License :: OSI Approved :: BSD License
Classifier: Natural Language :: English
Classifier: Programming Language :: Python :: 3 :: Only
